CLImail/__init__.py
CLImail/__main__.py
CLImail/classes.py
CLImail/tests.py
climail-2.1.5.dist-info/licenses/LICENSE
climail-2.1.5.dist-info/METADATA
climail-2.1.5.dist-info/WHEEL
climail-2.1.5.dist-info/top_level.txt
climail-2.1.5.dist-info/RECORD
