Metadata-Version: 2.4
Name: CLImail
Version: 2.1.5
Summary: A Command Line Interface email client written in python.
Home-page: https://github.com/HRLO77/CLImail
Author: HRLO77
Author-email: shakebmohammad.10@gmail.com
License: MIT
Classifier: Programming Language :: Python :: 3
Classifier: License :: OSI Approved :: MIT License
Classifier: Operating System :: OS Independent
License-File: LICENSE
Dynamic: author
Dynamic: author-email
Dynamic: classifier
Dynamic: description
Dynamic: description-content-type
Dynamic: home-page
Dynamic: license
Dynamic: license-file
Dynamic: summary
